_bleio/__init__.py
_bleio/address.py
_bleio/attribute.py
_bleio/characteristic_buffer.py
_bleio/common.py
_bleio/descriptor.py
_bleio/exceptions.py
_bleio/packet_buffer.py
_bleio/scan_entry.py
_bleio/uuid_.py
adafruit_blinka_bleio-4.1.2.dist-info/METADATA
adafruit_blinka_bleio-4.1.2.dist-info/WHEEL
adafruit_blinka_bleio-4.1.2.dist-info/top_level.txt
adafruit_blinka_bleio-4.1.2.dist-info/RECORD
