Metadata-Version: 2.1
Name: adafruit-blinka-bleio
Version: 4.1.2
Summary: `_bleio` for Blinka based on `bleak`
Author-email: Adafruit Industries <circuitpython@adafruit.com>
License: MIT
Project-URL: Homepage, https://github.com/adafruit/Adafruit_Blinka_bleio.git
Keywords: adafruit,blinka,circuitpython,micropython,blinka_bleio,bleio,bleak
Classifier: Intended Audience :: Developers
Classifier: Topic :: Software Development :: Libraries
Classifier: Topic :: Software Development :: Embedded Systems
Classifier: Topic :: System :: Hardware
Classifier: License :: OSI Approved :: MIT License
Classifier: Programming Language :: Python :: 3
Requires-Dist: Adafruit-Blinka
Requires-Dist: bleak
Provides-Extra: optional
